BRScraper/__init__.py
BRScraper/gleague.py
BRScraper/nba.py
BRScraper/international/__init__.py
BRScraper/international/aba.py
BRScraper/international/acb.py
BRScraper/international/cba.py
BRScraper/international/eurocup.py
BRScraper/international/euroleague.py
BRScraper/international/greece.py
BRScraper/international/israel.py
BRScraper/international/italy.py
BRScraper/international/lnb.py
BRScraper/international/nbl.py
BRScraper/international/olympics.py
BRScraper/international/players.py
BRScraper/international/russia.py
BRScraper/international/turkey.py
BRScraper-1.0.3.dist-info/LICENSE
BRScraper-1.0.3.dist-info/METADATA
BRScraper-1.0.3.dist-info/WHEEL
BRScraper-1.0.3.dist-info/top_level.txt
BRScraper-1.0.3.dist-info/RECORD
