Metadata-Version: 2.1
Name: BRScraper
Version: 1.0.3
Summary: Python module for Basketball Reference scraping and easy access to basketball data, including NBA, G League and international leagues
Home-page: https://github.com/GabrielPastorello/BRScraper
Author: Gabriel Speranza Pastorello
Author-email: gabriel.pastorello01@gmail.com
License: MIT
Keywords: basketball reference,scraper,nba,wnba,gleague,basketball,international basketball
Classifier: Programming Language :: Python :: 3
Classifier: License :: OSI Approved :: MIT License
Classifier: Operating System :: OS Independent
Requires-Python: >=3.6
License-File: LICENSE
Requires-Dist: pandas >=1.5.3
Requires-Dist: numpy >=1.24.4
Requires-Dist: python-dateutil >=2.8.2
Requires-Dist: pytz >=2023.3
